{"nodes": [{"id": "c_users_dell5_documents_dowiz_docs_audit_flow_radar_report_md", "label": "FLOW-RADAR-REPORT.md", "file_type": "document", "source_file": "C:\\Users\\Dell5\\Documents\\dowiz\\docs\\audit\\FLOW-RADAR-REPORT.md", "source_location": "L1"}, {"id": "audit_flow_radar_report_flow_radar_report_md_full_issue_matrix", "label": "FLOW-RADAR-REPORT.md \u2014 Full Issue Matrix", "file_type": "document", "source_file": "C:\\Users\\Dell5\\Documents\\dowiz\\docs\\audit\\FLOW-RADAR-REPORT.md", "source_location": "L1"}, {"id": "audit_flow_radar_report_executive_summary", "label": "Executive Summary", "file_type": "document", "source_file": "C:\\Users\\Dell5\\Documents\\dowiz\\docs\\audit\\FLOW-RADAR-REPORT.md", "source_location": "L9"}, {"id": "audit_flow_radar_report_critical_issues", "label": "\ud83d\udd34 Critical Issues", "file_type": "document", "source_file": "C:\\Users\\Dell5\\Documents\\dowiz\\docs\\audit\\FLOW-RADAR-REPORT.md", "source_location": "L21"}, {"id": "audit_flow_radar_report_1_settlements_endpoint_returns_500", "label": "1. Settlements endpoint returns 500", "file_type": "document", "source_file": "C:\\Users\\Dell5\\Documents\\dowiz\\docs\\audit\\FLOW-RADAR-REPORT.md", "source_location": "L23"}, {"id": "audit_flow_radar_report_2_backup_restore_test_degraded", "label": "2. Backup restore test degraded", "file_type": "document", "source_file": "C:\\Users\\Dell5\\Documents\\dowiz\\docs\\audit\\FLOW-RADAR-REPORT.md", "source_location": "L34"}, {"id": "audit_flow_radar_report_3_fallback_phone_coverage_at_0", "label": "3. Fallback phone coverage at 0%", "file_type": "document", "source_file": "C:\\Users\\Dell5\\Documents\\dowiz\\docs\\audit\\FLOW-RADAR-REPORT.md", "source_location": "L45"}, {"id": "audit_flow_radar_report_4_customer_push_subscription_endpoint_returns_400_for_owner_role", "label": "4. Customer push subscription endpoint returns 400 for owner role", "file_type": "document", "source_file": "C:\\Users\\Dell5\\Documents\\dowiz\\docs\\audit\\FLOW-RADAR-REPORT.md", "source_location": "L56"}, {"id": "audit_flow_radar_report_blocked_could_not_observe", "label": "\u26aa Blocked (could not observe)", "file_type": "document", "source_file": "C:\\Users\\Dell5\\Documents\\dowiz\\docs\\audit\\FLOW-RADAR-REPORT.md", "source_location": "L69"}, {"id": "audit_flow_radar_report_5_notification_audit_endpoint", "label": "5. Notification audit endpoint", "file_type": "document", "source_file": "C:\\Users\\Dell5\\Documents\\dowiz\\docs\\audit\\FLOW-RADAR-REPORT.md", "source_location": "L71"}, {"id": "audit_flow_radar_report_6_telegram_message_delivery_verification", "label": "6. Telegram message delivery verification", "file_type": "document", "source_file": "C:\\Users\\Dell5\\Documents\\dowiz\\docs\\audit\\FLOW-RADAR-REPORT.md", "source_location": "L79"}, {"id": "audit_flow_radar_report_passed_29_flows", "label": "\u2705 Passed (29 flows)", "file_type": "document", "source_file": "C:\\Users\\Dell5\\Documents\\dowiz\\docs\\audit\\FLOW-RADAR-REPORT.md", "source_location": "L89"}, {"id": "audit_flow_radar_report_static_analysis_results", "label": "Static Analysis Results", "file_type": "document", "source_file": "C:\\Users\\Dell5\\Documents\\dowiz\\docs\\audit\\FLOW-RADAR-REPORT.md", "source_location": "L103"}, {"id": "audit_flow_radar_report_cluster_by_root_cause", "label": "Cluster by Root Cause", "file_type": "document", "source_file": "C:\\Users\\Dell5\\Documents\\dowiz\\docs\\audit\\FLOW-RADAR-REPORT.md", "source_location": "L113"}, {"id": "audit_flow_radar_report_backlog_ordered_severity_effort", "label": "Backlog (ordered severity \u2192 effort)", "file_type": "document", "source_file": "C:\\Users\\Dell5\\Documents\\dowiz\\docs\\audit\\FLOW-RADAR-REPORT.md", "source_location": "L125"}, {"id": "audit_flow_radar_report_safety_confirmation", "label": "Safety Confirmation", "file_type": "document", "source_file": "C:\\Users\\Dell5\\Documents\\dowiz\\docs\\audit\\FLOW-RADAR-REPORT.md", "source_location": "L136"}], "edges": [{"source": "c_users_dell5_documents_dowiz_docs_audit_flow_radar_report_md", "target": "audit_flow_radar_report_flow_radar_report_md_full_issue_matrix", "relation": "contains", "confidence": "EXTRACTED", "source_file": "C:\\Users\\Dell5\\Documents\\dowiz\\docs\\audit\\FLOW-RADAR-REPORT.md", "source_location": "L1", "weight": 1.0}, {"source": "audit_flow_radar_report_flow_radar_report_md_full_issue_matrix", "target": "audit_flow_radar_report_executive_summary", "relation": "contains", "confidence": "EXTRACTED", "source_file": "C:\\Users\\Dell5\\Documents\\dowiz\\docs\\audit\\FLOW-RADAR-REPORT.md", "source_location": "L9", "weight": 1.0}, {"source": "audit_flow_radar_report_flow_radar_report_md_full_issue_matrix", "target": "audit_flow_radar_report_critical_issues", "relation": "contains", "confidence": "EXTRACTED", "source_file": "C:\\Users\\Dell5\\Documents\\dowiz\\docs\\audit\\FLOW-RADAR-REPORT.md", "source_location": "L21", "weight": 1.0}, {"source": "audit_flow_radar_report_critical_issues", "target": "audit_flow_radar_report_1_settlements_endpoint_returns_500", "relation": "contains", "confidence": "EXTRACTED", "source_file": "C:\\Users\\Dell5\\Documents\\dowiz\\docs\\audit\\FLOW-RADAR-REPORT.md", "source_location": "L23", "weight": 1.0}, {"source": "audit_flow_radar_report_critical_issues", "target": "audit_flow_radar_report_2_backup_restore_test_degraded", "relation": "contains", "confidence": "EXTRACTED", "source_file": "C:\\Users\\Dell5\\Documents\\dowiz\\docs\\audit\\FLOW-RADAR-REPORT.md", "source_location": "L34", "weight": 1.0}, {"source": "audit_flow_radar_report_critical_issues", "target": "audit_flow_radar_report_3_fallback_phone_coverage_at_0", "relation": "contains", "confidence": "EXTRACTED", "source_file": "C:\\Users\\Dell5\\Documents\\dowiz\\docs\\audit\\FLOW-RADAR-REPORT.md", "source_location": "L45", "weight": 1.0}, {"source": "audit_flow_radar_report_critical_issues", "target": "audit_flow_radar_report_4_customer_push_subscription_endpoint_returns_400_for_owner_role", "relation": "contains", "confidence": "EXTRACTED", "source_file": "C:\\Users\\Dell5\\Documents\\dowiz\\docs\\audit\\FLOW-RADAR-REPORT.md", "source_location": "L56", "weight": 1.0}, {"source": "audit_flow_radar_report_flow_radar_report_md_full_issue_matrix", "target": "audit_flow_radar_report_blocked_could_not_observe", "relation": "contains", "confidence": "EXTRACTED", "source_file": "C:\\Users\\Dell5\\Documents\\dowiz\\docs\\audit\\FLOW-RADAR-REPORT.md", "source_location": "L69", "weight": 1.0}, {"source": "audit_flow_radar_report_blocked_could_not_observe", "target": "audit_flow_radar_report_5_notification_audit_endpoint", "relation": "contains", "confidence": "EXTRACTED", "source_file": "C:\\Users\\Dell5\\Documents\\dowiz\\docs\\audit\\FLOW-RADAR-REPORT.md", "source_location": "L71", "weight": 1.0}, {"source": "audit_flow_radar_report_blocked_could_not_observe", "target": "audit_flow_radar_report_6_telegram_message_delivery_verification", "relation": "contains", "confidence": "EXTRACTED", "source_file": "C:\\Users\\Dell5\\Documents\\dowiz\\docs\\audit\\FLOW-RADAR-REPORT.md", "source_location": "L79", "weight": 1.0}, {"source": "audit_flow_radar_report_flow_radar_report_md_full_issue_matrix", "target": "audit_flow_radar_report_passed_29_flows", "relation": "contains", "confidence": "EXTRACTED", "source_file": "C:\\Users\\Dell5\\Documents\\dowiz\\docs\\audit\\FLOW-RADAR-REPORT.md", "source_location": "L89", "weight": 1.0}, {"source": "audit_flow_radar_report_flow_radar_report_md_full_issue_matrix", "target": "audit_flow_radar_report_static_analysis_results", "relation": "contains", "confidence": "EXTRACTED", "source_file": "C:\\Users\\Dell5\\Documents\\dowiz\\docs\\audit\\FLOW-RADAR-REPORT.md", "source_location": "L103", "weight": 1.0}, {"source": "audit_flow_radar_report_flow_radar_report_md_full_issue_matrix", "target": "audit_flow_radar_report_cluster_by_root_cause", "relation": "contains", "confidence": "EXTRACTED", "source_file": "C:\\Users\\Dell5\\Documents\\dowiz\\docs\\audit\\FLOW-RADAR-REPORT.md", "source_location": "L113", "weight": 1.0}, {"source": "audit_flow_radar_report_flow_radar_report_md_full_issue_matrix", "target": "audit_flow_radar_report_backlog_ordered_severity_effort", "relation": "contains", "confidence": "EXTRACTED", "source_file": "C:\\Users\\Dell5\\Documents\\dowiz\\docs\\audit\\FLOW-RADAR-REPORT.md", "source_location": "L125", "weight": 1.0}, {"source": "audit_flow_radar_report_flow_radar_report_md_full_issue_matrix", "target": "audit_flow_radar_report_safety_confirmation", "relation": "contains", "confidence": "EXTRACTED", "source_file": "C:\\Users\\Dell5\\Documents\\dowiz\\docs\\audit\\FLOW-RADAR-REPORT.md", "source_location": "L136", "weight": 1.0}], "input_tokens": 0, "output_tokens": 0}