{"nodes": [{"id": "c_users_dell5_documents_dowiz_docs_phase4_blockers_md", "label": "blockers.md", "file_type": "document", "source_file": "C:\\Users\\Dell5\\Documents\\dowiz\\docs\\phase4\\blockers.md", "source_location": "L1"}, {"id": "phase4_blockers_phase_4_blockers_open_questions_debt", "label": "Phase 4 \u2014 Blockers (Open Questions / Debt)", "file_type": "document", "source_file": "C:\\Users\\Dell5\\Documents\\dowiz\\docs\\phase4\\blockers.md", "source_location": "L1"}, {"id": "phase4_blockers_high_priority", "label": "High Priority", "file_type": "document", "source_file": "C:\\Users\\Dell5\\Documents\\dowiz\\docs\\phase4\\blockers.md", "source_location": "L7"}, {"id": "phase4_blockers_medium_priority", "label": "Medium Priority", "file_type": "document", "source_file": "C:\\Users\\Dell5\\Documents\\dowiz\\docs\\phase4\\blockers.md", "source_location": "L17"}, {"id": "phase4_blockers_low_priority", "label": "Low Priority", "file_type": "document", "source_file": "C:\\Users\\Dell5\\Documents\\dowiz\\docs\\phase4\\blockers.md", "source_location": "L27"}, {"id": "phase4_blockers_resolved_during_p23", "label": "Resolved During P23", "file_type": "document", "source_file": "C:\\Users\\Dell5\\Documents\\dowiz\\docs\\phase4\\blockers.md", "source_location": "L37"}], "edges": [{"source": "c_users_dell5_documents_dowiz_docs_phase4_blockers_md", "target": "phase4_blockers_phase_4_blockers_open_questions_debt", "relation": "contains", "confidence": "EXTRACTED", "source_file": "C:\\Users\\Dell5\\Documents\\dowiz\\docs\\phase4\\blockers.md", "source_location": "L1", "weight": 1.0}, {"source": "phase4_blockers_phase_4_blockers_open_questions_debt", "target": "phase4_blockers_high_priority", "relation": "contains", "confidence": "EXTRACTED", "source_file": "C:\\Users\\Dell5\\Documents\\dowiz\\docs\\phase4\\blockers.md", "source_location": "L7", "weight": 1.0}, {"source": "phase4_blockers_phase_4_blockers_open_questions_debt", "target": "phase4_blockers_medium_priority", "relation": "contains", "confidence": "EXTRACTED", "source_file": "C:\\Users\\Dell5\\Documents\\dowiz\\docs\\phase4\\blockers.md", "source_location": "L17", "weight": 1.0}, {"source": "phase4_blockers_phase_4_blockers_open_questions_debt", "target": "phase4_blockers_low_priority", "relation": "contains", "confidence": "EXTRACTED", "source_file": "C:\\Users\\Dell5\\Documents\\dowiz\\docs\\phase4\\blockers.md", "source_location": "L27", "weight": 1.0}, {"source": "phase4_blockers_phase_4_blockers_open_questions_debt", "target": "phase4_blockers_resolved_during_p23", "relation": "contains", "confidence": "EXTRACTED", "source_file": "C:\\Users\\Dell5\\Documents\\dowiz\\docs\\phase4\\blockers.md", "source_location": "L37", "weight": 1.0}], "input_tokens": 0, "output_tokens": 0}